dan.py
dan_annotation-0.1.0.dist-info/licenses/LICENSE
dan_annotation-0.1.0.dist-info/METADATA
dan_annotation-0.1.0.dist-info/WHEEL
dan_annotation-0.1.0.dist-info/top_level.txt
dan_annotation-0.1.0.dist-info/RECORD
