Metadata-Version: 2.4
Name: dan-annotation
Version: 0.1.0
Summary: DAN (Data Advanced Notation) Parser and Encoder for Python
Author: DAN Python Library
License-Expression: MIT
Project-URL: Documentation, https://github.com/marcuwynu23/danpy#readme
Project-URL: Issue Tracker, https://github.com/marcuwynu23/danpy/issues
Project-URL: Source Code, https://github.com/marcuwynu23/danpy
Keywords: dan,parser,encoder,data-format,configuration,config
Classifier: Development Status :: 4 - Beta
Classifier: Intended Audience :: Developers
Classifier: Programming Language :: Python :: 3
Classifier: Programming Language :: Python :: 3.7
Classifier: Programming Language :: Python :: 3.8
Classifier: Programming Language :: Python :: 3.9
Classifier: Programming Language :: Python :: 3.10
Classifier: Programming Language :: Python :: 3.11
Classifier: Programming Language :: Python :: 3.12
Classifier: Topic :: Software Development :: Libraries :: Python Modules
Classifier: Topic :: Text Processing :: Markup
Classifier: Topic :: Utilities
Requires-Python: >=3.7
License-File: LICENSE
Provides-Extra: dev
Requires-Dist: pytest>=7.0.0; extra == "dev"
Dynamic: license-file
